Workbook

Sheet Cumulative Budget
A1: Budget Category | B1: Year 1 | C1: Year 2 | D1: Year 3 | E1: Year 4 | F1: Year 5 | G1: Cumulative Total
A2: A. Senior Personnel | B2: ='Year 1'!B5 -> 82000 | C2: ='Year 2'!B5 -> 84460 | D2: ='Year 3'!B5 -> 86994 | E2: ='Year 4'!B5 -> 89603.89 | F2: ='Year 5'!B5 -> 92291.617 | G2: =SUM(B2:F2) -> 435349.51
A3: B. Other Personnel | B3: ='Year 1'!B10 -> 155000 | C3: ='Year 2'!B10 -> 159650 | D3: ='Year 3'!B10 -> 164440 | E3: ='Year 4'!B10 -> 169372.24 | F3: ='Year 5'!B10 -> 174454.06 | G3: =SUM(B3:F3) -> 822916.3
A4: C. Fringe Benefits | B4: ='Year 1'!B17 -> 103650 | C4: ='Year 2'!B17 -> 105238.5 | D4: ='Year 3'!B17 -> 106874.74 | E4: ='Year 4'!B17 -> 108559.93 | F4: ='Year 5'!B17 -> 110295.68 | G4: =SUM(B4:F4) -> 534618.85
A5: D. Equipment | B5: ='Year 1'!B21 -> 15000 | C5: ='Year 2'!B21 -> 0 | D5: ='Year 3'!B21 -> 0 | E5: ='Year 4'!B21 -> 6000 | F5: ='Year 5'!B21 -> 0 | G5: =SUM(B5:F5) -> 21000
A6: E. Travel | B6: ='Year 1'!B26 -> 2100 | C6: ='Year 2'!B26 -> 5800 | D6: ='Year 3'!B26 -> 0 | E6: ='Year 4'!B26 -> 5800 | F6: ='Year 5'!B26 -> 0 | G6: =SUM(B6:F6) -> 13700
A7: F. Participant Support Costs | B7: ='Year 1'!B30 -> 4000 | C7: ='Year 2'!B30 -> 2000 | D7: ='Year 3'!B30 -> 3600 | E7: ='Year 4'!B30 -> 8000 | F7: ='Year 5'!B30 -> 0 | G7: =SUM(B7:F7) -> 17600
A8: G. Other Direct Costs | B8: ='Year 1'!B34 -> 12000 | C8: ='Year 2'!B34 -> 10000 | D8: ='Year 3'!B34 -> 15000 | E8: ='Year 4'!B34 -> 15000 | F8: ='Year 5'!B35 -> 17000 | G8: =SUM(B8:F8) -> 69000
A10: H. Total Direct Costs | B10: =SUM(B2:B8) -> 373750 | C10: =SUM(C2:C8) -> 367148.5 | D10: =SUM(D2:D8) -> 376908.74 | E10: =SUM(E2:E8) -> 402336.06 | F10: =SUM(F2:F8) -> 394041.35 | G10: =SUM(B10:F10) -> 1914184.7
A12: I. Indirect Costs | B12: ='Year 1'!B38 -> 81756 | C12: ='Year 2'!B38 -> 83843.64 | D12: ='Year 3'!B38 -> 85994.098 | E12: ='Year 4'!B38 -> 88208.655 | F12: ='Year 5'!B39 -> 90489.925 | G12: =SUM(B12:F12) -> 430292.32
A14: J. Total Direct and Indirect Costs | B14: =B10+B12 -> 455506 | C14: =B10+B12 -> 455506 | D14: =B10+B12 -> 455506 | E14: =B10+B12 -> 455506 | F14: =B10+B12 -> 455506 | G14: =SUM(B14:F14) -> 2277530

Sheet Year 1
A1: NSF Budget Category | B1: Year 1 Requested Amount | C1: Notes
A2: A. Senior Personnel
A3: A.1 PI: Banister Bacon (1 mo summer) ($108,000 IBS) | B3: 12000 | C3: 3% annual escalation
A4: A.2 Data Scientist: Than Wiggins (12 mo calendar) ($70,000 IBS) | B4: 70000 | C4: 3% annual escalation
A5: Total A | B5: =SUM(B3:B4) -> 82000
A7: B. Other Personnel
A8: B.1 Postdoctoral Scholars (2 scholars @ $60,000 each) | B8: 120000 | C8: 3% annual escalation
A9: B.2 Graduate Students (5 students @ $70/hr for 100 hours each) | B9: 35000 | C9: 3% annual escalation
A10: Total B | B10: =SUM(B8:B9) -> 155000
A12: C. Fringe Benefits
A13: C.1 PI Fringe Benefits | B13: =0.25*B3 -> 3000 | C13: 25% of salary
A14: C.1 Data Scientist Fringe Benefits | B14: =0.25*B4+16900 -> 34400 | C14: 25% + $16,900 prorated for medical
A15: C.1 PDS Fringe Benefits | B15: =0.25*B8+16900*2 -> 63800 | C15: 25% + $16,900 prorated for medical
A16: C.1 GS Fringe Benefits | B16: =B9*0.07 -> 2450 | C16: 7% of wages
A17: Total C | B17: =SUM(B13:B16) -> 103650
A19: D. Equipment
A20: D.1 Uranium Paint Enricher | B20: 15000 | C20: BEARUranium 7UY-8JS, price obtained from vendor bidding process initiated by purchasing department
A21: Total D | B21: =SUM(B20:B20) -> 15000
A23: E. Travel
A24: E.1 Domestic Travel | B24: =1050*2 -> 2100 | C24: Travel to Los Alamos, NM for 2 people for Uranium Enrichment Training - Each person will have airfare $600, lodging $300, per diem $150, $1,050 each
A25: E.2 Foreign Travel | B25: 0
A26: Total E | B26: =SUM(B24:B25) -> 2100
A28: F. Participant Support Costs
A29: F.1 Travel | B29: =800*5 -> 4000 | C29: Funds for 5 trainees to travel to Piglan, WY to obtain training during the statue enrichment process - Each participant will have airfare $400, lodging $250, per diem $150, $800 each
A30: Total F | B30: =SUM(B29:B29) -> 4000
A32: G. Other Direct Costs
A33: G.3 Consultant | B33: =400*30 -> 12000 | C33: Pynk Panthyr, uranium evaluation expert, $400 per day, 30 days
A34: Total G | B34: =SUM(B33:B33) -> 12000
A36: H. Total Direct Costs (A through G) | B36: =B5+B10+B17+B21+B26+B30+B34 -> 373750
A38: I. Indirect Costs (F&A @ 24% SWB) | B38: =(B5+B10+B17)*0.24 -> 81756 | C38: Base: $340,650
A40: J. Total Direct and Indirect Costs (H + I) | B40: =B36+B38 -> 455506

Sheet Year 2
A1: NSF Budget Category | B1: Year 2 Requested Amount | C1: Notes
A2: A. Senior Personnel
A3: A.1 PI: Banister Bacon (1 mo summer) | B3: 12360 | C3: 3% annual escalation
A4: A.2 Data Scientist: Than Wiggins (12 mo calendar) | B4: =1.03*'Year 1'!B4 -> 72100 | C4: 3% annual escalation
A5: Total A | B5: =SUM(B3:B4) -> 84460
A7: B. Other Personnel
A8: B.1 Postdoctoral Scholars | B8: =1.03*'Year 1'!B8 -> 123600 | C8: 3% annual escalation
A9: B.2 Graduate Students | B9: 36050 | C9: 3% annual escalation
A10: Total B | B10: =SUM(B8:B9) -> 159650
A12: C. Fringe Benefits
A13: C.1 PI Fringe Benefits | B13: =0.25*B3 -> 3090 | C13: 25% of salary
A14: C.1 Data Scientist Fringe Benefits | B14: =0.25*B4+16900 -> 34925 | C14: 25% + $16,900 prorated for medical
A15: C.1 PDS Fringe Benefits | B15: =0.25*B8+16900*2 -> 64700 | C15: 25% + $16,900 prorated for medical
A16: C.1 GS Fringe Benefits | B16: =B9*0.07 -> 2523.5 | C16: 7% of wages
A17: Total C | B17: =SUM(B13:B16) -> 105238.5
A19: D. Equipment
B20: 0
A21: Total D | B21: =SUM(B20:B20) -> 0
A23: E. Travel
A24: E.1 Domestic Travel | B24: 0
A25: E.2 Foreign Travel | B25: =2900*2 -> 5800 | C25: Travel to Rome, Italy for 2 people for Conference Presentations on Findings - Each person will have airfare $1,500, lodging $800, per diem $600, $2,900 each
A26: Total E | B26: =SUM(B24:B25) -> 5800
A28: F. Participant Support Costs
A29: F.1 Stipends | B29: =500*4 -> 2000 | C29: Stipends for 4 participants to attend a uranium enrichment conference to be held at Piglan University, $500 each
A30: Total F | B30: =SUM(B29:B29) -> 2000
A32: G. Other Direct Costs
A33: G.1 Materials and Supplies | B33: 10000 | C33: 10 hazmat suits, $1,000 each
A34: Total G | B34: =SUM(B33:B33) -> 10000
A36: H. Total Direct Costs (A through G) | B36: =B5+B10+B17+B21+B26+B30+B34 -> 367148.5
A38: I. Indirect Costs (F&A @ 24% SWB) | B38: =(B5+B10+B17)*0.24 -> 83843.64 | C38: Base: $349,349
A40: J. Total Direct and Indirect Costs (H + I) | B40: =B36+B38 -> 450992.14

Sheet Year 3
A1: NSF Budget Category | B1: Year 3 Requested Amount | C1: Notes
A2: A. Senior Personnel
A3: A.1 PI: Banister Bacon (1 mo summer) | B3: 12731 | C3: 3% annual escalation
A4: A.2 Data Scientist: Than Wiggins (12 mo calendar) | B4: =1.03*'Year 2'!B4 -> 74263 | C4: 3% annual escalation
A5: Total A | B5: =SUM(B3:B4) -> 86994
A7: B. Other Personnel
A8: B.1 Postdoctoral Scholars | B8: ='Year 2'!B8*1.03 -> 127308 | C8: 3% annual escalation
A9: B.2 Graduate Students | B9: 37132 | C9: 3% annual escalation
A10: Total B | B10: =SUM(B8:B9) -> 164440
A12: C. Fringe Benefits
A13: C.1 PI Fringe Benefits | B13: =0.25*B3 -> 3182.75 | C13: 25% of salary
A14: C.1 Data Scientist Fringe Benefits | B14: =0.25*B4+16900 -> 35465.75 | C14: 25% + $16,900 prorated for medical
A15: C.1 PDS Fringe Benefits | B15: =0.25*B8+16900*2 -> 65627 | C15: 25% + $16,900 prorated for medical
A16: C.1 GS Fringe Benefits | B16: =B9*0.07 -> 2599.24 | C16: 7% of wages
A17: Total C | B17: =SUM(B13:B16) -> 106874.74
A19: D. Equipment
B20: 0
A21: Total D | B21: =SUM(B20:B20) -> 0
A23: E. Travel
A24: E.1 Domestic Travel | B24: 0
A25: E.2 Foreign Travel | B25: 0
A26: Total E | B26: =SUM(B24:B25) -> 0
A28: F. Participant Support Costs
A29: F.1 Subsistence | B29: =1200*3 -> 3600 | C29: Funds to house 3 uranium visiting external graduate students during the enrichment process for one month, $1,200 each
A30: Total F | B30: =SUM(B29:B29) -> 3600
A32: G. Other Direct Costs
A33: G.6 Other (Tuition) | B33: 15000 | C33: For 5 Graduate Students
A34: Total G | B34: =SUM(B33:B33) -> 15000
A36: H. Total Direct Costs (A through G) | B36: =B5+B10+B17+B21+B26+B30+B34 -> 376908.74
A38: I. Indirect Costs (F&A @ 24% SWB) | B38: =(B5+B10+B17)*0.24 -> 85994.098 | C38: Base: $358,309
A40: J. Total Direct and Indirect Costs (H + I) | B40: =B36+B38 -> 462902.84

Sheet Year 4
A1: NSF Budget Category | B1: Year 4 Requested Amount | C1: Notes
A2: A. Senior Personnel
A3: A.1 PI: Banister Bacon (1 mo summer) | B3: 13113 | C3: 3% annual escalation
A4: A.2 Data Scientist: Than Wiggins (12 mo calendar) | B4: =1.03*'Year 3'!B4 -> 76490.89 | C4: 3% annual escalation
A5: Total A | B5: =SUM(B3:B4) -> 89603.89
A7: B. Other Personnel
A8: B.1 Postdoctoral Scholars | B8: =1.03*'Year 3'!B8 -> 131127.24 | C8: 3% annual escalation
A9: B.2 Graduate Students | B9: 38245 | C9: 3% annual escalation
A10: Total B | B10: =SUM(B8:B9) -> 169372.24
A12: C. Fringe Benefits
A13: C.1 PI Fringe Benefits | B13: =0.25*B3 -> 3278.25 | C13: 25% of salary
A14: C.1 Data Scientist Fringe Benefits | B14: =0.25*B4+16900 -> 36022.723 | C14: 25% + $16,900 prorated for medical
A15: C.1 PDS Fringe Benefits | B15: =0.25*B8+16900*2 -> 66581.81 | C15: 25% + $16,900 prorated for medical
A16: C.1 GS Fringe Benefits | B16: =B9*0.07 -> 2677.15 | C16: 7% of wages
A17: Total C | B17: =SUM(B13:B16) -> 108559.93
A19: D. Equipment
A20: D.2 Uranium Disposal System | B20: 6000 | C20: Model UX-8800, current market price
A21: Total D | B21: =SUM(B20:B20) -> 6000
A23: E. Travel
A24: E.1 Domestic Travel | B24: 0
A25: E.2 Foreign Travel | B25: =2900*2 -> 5800 | C25: Travel to Rome, Italy for 2 people for Conference Presentations on Findings - Each person will have airfare $1,500, lodging $800, per diem $600, $2,900 each
A26: Total E | B26: =SUM(B24:B25) -> 5800
A28: F. Participant Support Costs
A29: F.1 Other | B29: =400*20 -> 8000 | C29: Cleanroom instructional kit access charages for 20 public site trainees, $400 each
A30: Total F | B30: =SUM(B29:B29) -> 8000
A32: G. Other Direct Costs
A33: G.6 Other (Tuition) | B33: 15000 | C33: For 5 Graduate Students
A34: Total G | B34: =SUM(B33:B33) -> 15000
A36: H. Total Direct Costs (A through G) | B36: =B5+B10+B17+B21+B26+B30+B34 -> 402336.06
A38: I. Indirect Costs (F&A @ 24% SWB) | B38: =(B5+B10+B17)*0.24 -> 88208.655 | C38: Base: $367,536
A40: J. Total Direct and Indirect Costs (H + I) | B40: =B36+B38 -> 490544.72

Sheet Year 5
A1: NSF Budget Category | B1: Year 5 Requested Amount | C1: Notes
A2: A. Senior Personnel
A3: A.1 PI: Banister Bacon (1 mo summer) | B3: 13506 | C3: 3% annual escalation
A4: A.2 Data Scientist: Than Wiggins (12 mo calendar) | B4: =1.03*'Year 4'!B4 -> 78785.617 | C4: 3% annual escalation
A5: Total A | B5: =SUM(B3:B4) -> 92291.617
A7: B. Other Personnel
A8: B.1 Postdoctoral Scholars | B8: ='Year 4'!B8*1.03 -> 135061.06 | C8: 3% annual escalation
A9: B.2 Graduate Students | B9: 39393 | C9: 3% annual escalation
A10: Total B | B10: =SUM(B8:B9) -> 174454.06
A12: C. Fringe Benefits
A13: C.1 PI Fringe Benefits | B13: =0.25*B3 -> 3376.5 | C13: 25% of salary
A14: C.1 Data Scientist Fringe Benefits | B14: =0.25*B4+16900 -> 36596.404 | C14: 25% + $16,900 prorated for medical
A15: C.1 PDS Fringe Benefits | B15: =0.25*B8+16900*2 -> 67565.264 | C15: 25% + $16,900 prorated for medical
A16: C.1 GS Fringe Benefits | B16: =B9*0.07 -> 2757.51 | C16: 7% of wages
A17: Total C | B17: =SUM(B13:B16) -> 110295.68
A19: D. Equipment
B20: 0
A21: Total D | B21: =SUM(B20:B20) -> 0
A23: E. Travel
A24: E.1 Domestic Travel | B24: 0
A25: E.2 Foreign Travel | B25: 0
A26: Total E | B26: =SUM(B24:B25) -> 0
A28: F. Participant Support Costs
B29: 0
A30: Total F | B30: =SUM(B29:B29) -> 0
A32: G. Other Direct Costs
A33: G.2 Publication Costs/Documentation | B33: 2000
A34: G.6 Other (Tuition) | B34: 15000 | C34: For 5 Graduate Students
A35: Total G | B35: =SUM(B33:B34) -> 17000
A37: H. Total Direct Costs (A through G) | B37: =B5+B10+B17+B21+B26+B30+B35 -> 394041.35
A39: I. Indirect Costs (F&A @ 24% SWB) | B39: =(B5+B10+B17)*0.24 -> 90489.925 | C39: Base: $388,041
A41: J. Total Direct and Indirect Costs (H + I) | B41: =B37+B39 -> 484531.28
